MANIFEST.in
README
setup.py
tagger.py
bin/lsotag
bin/lstag
bin/rmtag
bin/tag
bin/tagger
simple_tagger.egg-info/PKG-INFO
simple_tagger.egg-info/SOURCES.txt
simple_tagger.egg-info/dependency_links.txt
simple_tagger.egg-info/not-zip-safe
simple_tagger.egg-info/requires.txt
simple_tagger.egg-info/top_level.txt