Metadata-Version: 1.1
Name: simple-tagger
Version: 0.6
Summary: Simple console tool for manage tags on files and directories
Home-page: https://github.com/amrichko/tagger.git
Author: Andrey Mrichko
Author-email: andymrk2@gmail.com
License: GPLv3
Keywords: tag tagger files folders directories
Platform: UNKNOWN
Classifier: Development Status :: 5 - Production/Stable
Classifier: Environment :: Console
Classifier: Intended Audience :: End Users/Desktop
Classifier: License :: OSI Approved :: GNU General Public License v3 (GPLv3)
Classifier: Natural Language :: English
Classifier: Operating System :: POSIX :: Linux
Classifier: Programming Language :: Python :: 3.5
Classifier: Topic :: System :: Filesystems
